pbf_file_size_estimation/__init__.py
pbf_file_size_estimation/app_settings.py
pbf_file_size_estimation/apps.py
pbf_file_size_estimation/estimate_size.py
pbf_file_size_estimation/planet-stats.csv
pbf_file_size_estimation/serializers.py
pbf_file_size_estimation/views.py
geometalab.osm_pbf_file_size_estimation_service-3.0.0.dist-info/LICENSE
geometalab.osm_pbf_file_size_estimation_service-3.0.0.dist-info/WHEEL
geometalab.osm_pbf_file_size_estimation_service-3.0.0.dist-info/METADATA
geometalab.osm_pbf_file_size_estimation_service-3.0.0.dist-info/RECORD
