Metadata-Version: 2.1
Name: geometalab.osm-pbf-file-size-estimation-service
Version: 3.0.0
Summary: Rough pbf estimate of a certain extent.
Home-page: https://github.com/geometalab/osm-pbf-file-size-estimation-service
License: MIT
Author: Geometa Lab
Author-email: geometalab@hsr.ch
Requires-Python: >=3.7,<4.0
Classifier: License :: OSI Approved :: MIT License
Classifier: Programming Language :: Python :: 3
Classifier: Programming Language :: Python :: 3.7
Classifier: Programming Language :: Python :: 3.8
Classifier: Programming Language :: Python :: 3.9
Requires-Dist: djangorestframework (>=3.12.4,<4.0.0)
Project-URL: Repository, https://github.com/geometalab/osm-pbf-file-size-estimation-service
